pyro_client/loader.py
pyro_client/storage.py
pyro_client/client/base.py
pyro_client/client/bot.py
pyro_client/client/dc.json
pyro_client/client/file.py
pyro_client/client/filler.py
pyro_client/client/user.py
pyrogram_client-0.0.9.dist-info/METADATA
pyrogram_client-0.0.9.dist-info/WHEEL
pyrogram_client-0.0.9.dist-info/top_level.txt
pyrogram_client-0.0.9.dist-info/RECORD
