Metadata-Version: 2.4
Name: pyrogram-client
Version: 0.0.9
Author-email: Mike Artemiev <mixartemev@gmail.com>
Project-URL: Homepage, https://gitlab.com/XyncNet/pyro-client
Project-URL: Repository, https://gitlab.com/XyncNet/pyro-client
Requires-Python: >=3.11
Requires-Dist: kurigram
Requires-Dist: tgcrypto
Requires-Dist: xn-auth
Provides-Extra: dev
Requires-Dist: build; extra == "dev"
Requires-Dist: pre-commit; extra == "dev"
Requires-Dist: python-dotenv; extra == "dev"
Requires-Dist: setuptools-scm; extra == "dev"
Requires-Dist: twine; extra == "dev"
